pelican/plugins/pelican_algolia/__init__.py
pelican/plugins/pelican_algolia/pelican_algolia.py
pelican_algolia-2.2.0.dist-info/LICENSE
pelican_algolia-2.2.0.dist-info/WHEEL
pelican_algolia-2.2.0.dist-info/METADATA
pelican_algolia-2.2.0.dist-info/RECORD
