Metadata-Version: 2.1
Name: pelican-algolia
Version: 2.2.0
Summary: Plugin to integrate Algolia Search with Pelican SSG
Home-page: https://github.com/rehanhaider/pelican-algolia
License: AGPL-3.0
Keywords: pelican,plugin,algolia,search,tipue
Author: Rehan Haider
Author-email: email@rehanhaider.com
Requires-Python: >=3.6.2,<4.0
Classifier: Development Status :: 5 - Production/Stable
Classifier: Environment :: Console
Classifier: Framework :: Pelican
Classifier: Framework :: Pelican :: Plugins
Classifier: Intended Audience :: End Users/Desktop
Classifier: License :: OSI Approved :: GNU Affero General Public License v3
Classifier: Operating System :: OS Independent
Classifier: Programming Language :: Python
Classifier: Programming Language :: Python :: 3
Classifier: Programming Language :: Python :: 3.10
Classifier: Programming Language :: Python :: 3.7
Classifier: Programming Language :: Python :: 3.8
Classifier: Programming Language :: Python :: 3.9
Classifier: Topic :: Internet :: WWW/HTTP
Classifier: Topic :: Software Development :: Libraries :: Python Modules
Provides-Extra: markdown
Requires-Dist: algoliasearch (>=2.6.0)
Requires-Dist: markdown (>=3.2); extra == "markdown"
Requires-Dist: pelican (>=4.5)
Project-URL: Documentation, https://docs.getpelican.com
Project-URL: Issue Tracker, https://github.com/rehanhaider/pelican-algolia/issues
Project-URL: Repository, https://github.com/rehanhaider/pelican-algolia
